just_solve_10.py
setup.py
just_solve_10.egg-info/PKG-INFO
just_solve_10.egg-info/SOURCES.txt
just_solve_10.egg-info/dependency_links.txt
just_solve_10.egg-info/entry_points.txt
just_solve_10.egg-info/top_level.txt