Metadata-Version: 1.0
Name: just_solve_10
Version: 0.0.0post1
Summary: Tentative project
Home-page: https://github.com/ioltuszyk/just-solve-10
Author: Ian Oltuszyk
Author-email: ian.oltu@gmail.com
License: MIT License
Platform: UNKNOWN
